.readthedocs.yaml
CHANGES.rst
CONTRIBUTING.rst
LICENSE
MANIFEST.in
Makefile
README.rst
RELEASES.rst
requirements-dev.txt
setup.py
tox.ini
authtools/__init__.py
authtools/admin.py
authtools/apps.py
authtools/backends.py
authtools/forms.py
authtools/models.py
authtools/migrations/0001_initial.py
authtools/migrations/0002_django18.py
authtools/migrations/0003_auto_20160128_0912.py
authtools/migrations/__init__.py
django_authtools.egg-info/PKG-INFO
django_authtools.egg-info/SOURCES.txt
django_authtools.egg-info/dependency_links.txt
django_authtools.egg-info/not-zip-safe
django_authtools.egg-info/requires.txt
django_authtools.egg-info/top_level.txt
docs/Makefile
docs/admin.rst
docs/backends.rst
docs/changelog.rst
docs/conf.py
docs/contributing.rst
docs/forms.rst
docs/index.rst
docs/intro.rst
docs/talks.rst
docs/_ext/djangodocs.py
docs/_themes/kr/layout.html
docs/_themes/kr/relations.html
docs/_themes/kr/theme.conf
docs/_themes/kr/static/flasky.css_t
docs/_themes/kr/static/small_flask.css
docs/how-to/admin.py
docs/how-to/index.rst
docs/how-to/invitation-email.rst
docs/how-to/migrate-to-a-custom-user-model.rst
tests/manage.py
tests/tests/__init__.py
tests/tests/models.py
tests/tests/settings.py
tests/tests/sqlite_test_settings.py
tests/tests/tests.py
tests/tests/urls.py
tests/tests/fixtures/authtoolstestdata.json
tests/tests/fixtures/customusertestdata.json
tests/tests/migrations/0001_initial.py
tests/tests/migrations/__init__.py